lib/__init__.py
lib/crypter.py
objcrypt-0.1.data/scripts/objcrypt
objcrypt-0.1.dist-info/METADATA
objcrypt-0.1.dist-info/WHEEL
objcrypt-0.1.dist-info/top_level.txt
objcrypt-0.1.dist-info/RECORD
